Diagnostictable.py
Diagnostictable-0.0.1.dist-info/LICENSE.txt.txt
Diagnostictable-0.0.1.dist-info/METADATA
Diagnostictable-0.0.1.dist-info/WHEEL
Diagnostictable-0.0.1.dist-info/top_level.txt
Diagnostictable-0.0.1.dist-info/RECORD
